thebeans/CSVtoDF.py
thebeans/__init__.py
thebeans/common.py
thebeans/foliummap.py
thebeans/thebeans.py
TheBeans-0.1.0.dist-info/LICENSE
TheBeans-0.1.0.dist-info/METADATA
TheBeans-0.1.0.dist-info/WHEEL
TheBeans-0.1.0.dist-info/entry_points.txt
TheBeans-0.1.0.dist-info/top_level.txt
TheBeans-0.1.0.dist-info/RECORD
