Metadata-Version: 2.1
Name: TheBeans
Version: 0.1.0
Summary: Python package with the beans.
Author-email: Lucas Phillips <lphill57@vols.utk.edu>
License: MIT License
Project-URL: Homepage, https://github.com/phillipslucas/TheBeans
Keywords: TheBeans
Classifier: Intended Audience :: Developers
Classifier: License :: OSI Approved :: MIT License
Classifier: Natural Language :: English
Classifier: Programming Language :: Python :: 3.8
Classifier: Programming Language :: Python :: 3.9
Classifier: Programming Language :: Python :: 3.10
Classifier: Programming Language :: Python :: 3.11
Classifier: Programming Language :: Python :: 3.12
Requires-Python: >=3.8
License-File: LICENSE
Requires-Dist: numpy
Requires-Dist: ipyleaflet
Requires-Dist: ipywidgets
Requires-Dist: pysheds
Requires-Dist: pandas
Requires-Dist: geopandas
Requires-Dist: matplotlib
Provides-Extra: all
Requires-Dist: TheBeans[extra] ; extra == 'all'
Provides-Extra: extra
Requires-Dist: pandas ; extra == 'extra'
